Milestone2_Single Cycle/00_src/add_sub.sv
module add_sub #(parameter data_size = 4)
(
    input logic [data_size-1:0]  X, 
    input logic [data_size-1:0]  Y, 
    input logic                  Cin,           //

    output logic [data_size-1:0] S
    // output logic                 Co
);

    logic cout;

    // ksa_adder #(data_size) adder (X, {data_size{Cin}}^Y, Cin, S, cout);
    assign S = X + ({data_size{Cin}} ^ Y ) + Cin;
    // assign Co = cout^Cin;           

endmodule

Milestone2_Single Cycle/01_bench/adder_tb.sv
module add_sub_tb #(
    parameter DATA_SIZE = 32
)();
    logic [DATA_SIZE-1:0] a, b;
    logic [DATA_SIZE-1:0] sum;
    logic select;
    logic c;
    logic [DATA_SIZE-1:0] expected;
    int sub_errors = 0;
    int add_errors = 0; 

    add_sub #(DATA_SIZE) dut(a, b, select, sum);

    initial begin
        $dumpfile("add_sub_tb.vcd");
        $dumpvars(0, add_sub_tb);
    end

    initial begin
        for(int i = 0; i < 2**10; i++) begin
            a = $urandom;
            b = $urandom;
            select = $urandom_range(0, 1);
            #5;
            expected = (select) ? a - b : a + b;
            if (sum !== expected) begin
                $display("Error: a = %d, b = %d, select = %b, sum = %b, expected = %b",
                        a, b, select, sum, expected);
                if (select) begin
                    sub_errors++;
                end
                else begin
                    add_errors++;
                end
            end
        end
        $display("Test finished with %3d subtraction errors.", sub_errors);
        $display("Test finished with %3d addition errors.", add_errors);
    end
endmodule

Milestone2_Single Cycle/03_test/add_sub_tb.vcd
$date
	Thu Nov 28 21:55:45 2024
$end
$version
	Icarus Verilog
$end
$timescale
	1s
$end
$scope module add_sub_tb $end
$var wire 32 ! sum [31:0] $end
$var parameter 32 " DATA_SIZE $end
$var reg 32 # a [31:0] $end
$var reg 32 $ b [31:0] $end
$var reg 32 % expected [31:0] $end
$var reg 1 & select $end
$var integer 32 ' add_errors [31:0] $end
$var integer 32 ( sub_errors [31:0] $end
$scope module dut $end
$var wire 1 & Cin $end
$var wire 32 ) X [31:0] $end
$var wire 32 * Y [31:0] $end
$var wire 32 + S [31:0] $end
$var parameter 32 , data_size $end
$upscope $end
$scope begin $ivl_for_loop0 $end
$var integer 32 - i [31:0] $end
$upscope $end
$upscope $end
$enddefinitions $end
$comment Show the parameter values. $end
$dumpall
b100000 ,
b100000 "
$end
#0
$dumpvars
b0 -
b11010010100111101001001110100101 +
b1000000100010010101111010000001 *
b10010010000101010011010100100100 )
b0 (
b0 '
0&
bx %
b1000000100010010101111010000001 $
b10010010000101010011010100100100 #
b11010010100111101001001110100101 !
$end
#5
1&
b10000110101110010111101100001101 $
b10000110101110010111101100001101 *
b10101011001101101101101101010110 !
b10101011001101101101101101010110 +
b110001111100000101011001100011 #
b110001111100000101011001100011 )
b1 -
b11010010100111101001001110100101 %
#10
b1001001101110101001000010010 $
b1001001101110101001000010010 *
b101001100010110011001001010011 !
b101001100010110011001001010011 +
b110010110000101000010001100101 #
b110010110000101000010001100101 )
b10 -
b10101011001101101101101101010110 %
#15
b10111011001000111111000101110110 $
b10111011001000111111000101110110 *
b11001011101100111101101110010111 !
b11001011101100111101101110010111 +
b10000110110101111100110100001101 #
b10000110110101111100110100001101 )
b11 -
b101001100010110011001001010011 %
#20
b11000110001011011111011110001100 $
b11000110001011011111011110001100 *
b110000101001100110000001100001 !
b110000101001100110000001100001 +
b11110110110101000101011111101101 #
b11110110110101000101011111101101 )
b100 -
b11001011101100111101101110010111 %
#25
0&
b1100010111101111000010011000101 $
b1100010111101111000010011000101 *
b11000110001011101010100110001011 !
b11000110001011101010100110001011 +
b1100011001101110010010011000110 #
b1100011001101110010010011000110 )
b101 -
b110000101001100110000001100001 %
#30
b111011110100100111001001110111 $
b111011110100100111001001110111 *
b101110100000100110101001011100 !
b101110100000100110101001011100 +
b11110010101011111111011111100101 #
b11110010101011111111011111100101 )
b110 -
b11000110001011101010100110001011 %
#35
b11111001001100000110100111110010 $
b11111001001100000110100111110010 *
b11000001000111010100010110000001 !
b11000001000111010100010110000001 +
b11000111111011001101101110001111 #
b11000111111011001101101110001111 )
b111 -
b101110100000100110101001011100 %
#40
1&
b1100010110010100100111011000101 $
b1100010110010100100111011000101 *
b10001001101100010110000100011 !
b10001001101100010110000100011 +
b1110100000000000111101011101000 #
b1110100000000000111101011101000 )
b1000 -
b11000001000111010100010110000001 %
#45
0&
b10110101010110101100000101101 $
b10110101010110101100000101101 *
b1110101001110011000000011101010 !
b1110101001110011000000011101010 +
b1011110100011100010100010111101 #
b1011110100011100010100010111101 )
b1001 -
b10001001101100010110000100011 %
#50
b10000101011100111000011100001010 $
b10000101011100111000011100001010 *
b10110111011000101110100101101101 !
b10110111011000101110100101101101 +
b110001111011110110001001100011 #
b110001111011110110001001100011 )
b1010 -
b1110101001110011000000011101010 %
#55
b11010101011110000100010110101010 $
b11010101011110000100010110101010 *
b1100101110111000110011011001010 !
b1100101110111000110011011001010 +
b10010000011001000010000100100000 #
b10010000011001000010000100100000 )
b1011 -
b10110111011000101110100101101101 %
#60
b1001100000111011100000010011 $
b1001100000111011100000010011 *
b1010100101000111111011010101001 !
b1010100101000111111011010101001 +
b1001011001000000011111010010110 #
b1001011001000000011111010010110 )
b1100 -
b1100101110111000110011011001010 %
#65
b10110101100111111101110101101011 $
b10110101100111111101110101101011 *
b11011111010001111011001110111110 !
b11011111010001111011001110111110 +
b101001101001111101011001010011 #
b101001101001111101011001010011 )
b1101 -
b1010100101000111111011010101001 %
#70
1&
b1010111010101100011111010101110 $
b1010111010101100011111010101110 *
b10101001110000010000101101010100 !
b10101001110000010000101101010100 +
b1000101110100101000000010 #
b1000101110100101000000010 )
b1110 -
b11011111010001111011001110111110 %
#75
b10010001100001000100100100100011 $
b10010001100001000100100100100011 *
b11010110010000010010100110101100 !
b11010110010000010010100110101100 +
b1100111110001010111001011001111 #
b1100111110001010111001011001111 )
b1111 -
b10101001110000010000101101010100 %
#80
b11110001100010100110000111100 $
b11110001100010100110000111100 *
b1000111010000011011111010001110 !
b1000111010000011011111010001110 +
b1100101011100110000101011001010 #
b1100101011100110000101011001010 )
b10000 -
b11010110010000010010100110101100 %
#85
0&
b10100000110001001011001101000001 $
b10100000110001001011001101000001 *
b1100101111100110001010011001011 !
b1100101111100110001010011001011 +
b11000101001011100110000110001010 #
b11000101001011100110000110001010 )
b10001 -
b1000111010000011011111010001110 %
#90
1&
b1000100100010100001001010001001 $
b1000100100010100001001010001001 *
b1110111100101101110000011101111 !
b1110111100101101110000011101111 +
b10111100001000001111001101111000 #
b10111100001000001111001101111000 )
b10010 -
b1100101111100110001010011001011 %
#95
b11100011010010111111100111000110 $
b11100011010010111111100111000110 *
b11110111101101100110101111110000 !
b11110111101101100110101111110000 +
b11011011000000100110010110110110 #
b11011011000000100110010110110110 )
b10011 -
b1110111100101101110000011101111 %
#100
0&
b10010101000011111101110100101010 $
b10010101000011111101110100101010 *
b11110011100001001101111111100110 !
b11110011100001001101111111100110 +
b1011110011101010000001010111100 #
b1011110011101010000001010111100 )
b10100 -
b11110111101101100110101111110000 %
#105
1&
b11000010111100100100000110000101 $
b11000010111100100100000110000101 *
b1110101101001010111110011101100 !
b1110101101001010111110011101100 +
b111000100101111011111001110001 #
b111000100101111011111001110001 )
b10101 -
b11110011100001001101111111100110 %
#110
0&
b10011101000001100011001100111010 $
b10011101000001100011001100111010 *
b10111010110100101001001101110101 !
b10111010110100101001001101110101 +
b11101110011000110000000111011 #
b11101110011000110000000111011 )
b10110 -
b1110101101001010111110011101100 %
#115
1&
b11111000110110011001101111110001 $
b11111000110110011001101111110001 *
b10010001110100001010111100100100 !
b10010001110100001010111100100100 +
b10001010101010100100101100010101 #
b10001010101010100100101100010101 )
b10111 -
b10111010110100101001001101110101 %
#120
b10100110001101011111101101001100 $
b10100110001101011111101101001100 *
b1010111011010000110000010110 !
b1010111011010000110000010110 +
b10110001001000110000011101100010 #
b10110001001000110000011101100010 )
b11000 -
b10010001110100001010111100100100 %
#125
0&
b11111100011011011010100111111000 $
b11111100011011011010100111111000 *
b11000100001001110100101110000111 !
b11000100001001110100101110000111 +
b11000111101110011010000110001111 #
b11000111101110011010000110001111 )
b11001 -
b1010111011010000110000010110 %
#130
b101110011111011001010001011100 $
b101110011111011001010001011100 *
b1111110010000011110101011111011 !
b1111110010000011110101011111011 +
b1001111110001000101011010011111 #
b1001111110001000101011010011111 )
b11010 -
b11000100001001110100101110000111 %
#135
b100100101011100011001001001001 $
b100100101011100011001001001001 *
b11101001100011000110100111010010 !
b11101001100011000110100111010010 +
b11000100110111100011011110001001 #
b11000100110111100011011110001001 )
b11011 -
b1111110010000011110101011111011 %
#140
1&
b101000110001111111110001010001 $
b101000110001111111110001010001 *
b1000011001101101100010010000110 !
b1000011001101101100010010000110 +
b1101011111111101100000011010111 #
b1101011111111101100000011010111 )
b11100 -
b11101001100011000110100111010010 %
#145
b1100001001011001100111011000010 $
b1100001001011001100111011000010 *
b100100111100001011000001001010 !
b100100111100001011000001001010 +
b10000110000111010111111100001100 #
b10000110000111010111111100001100 )
b11101 -
b1000011001101101100010010000110 %
#150
b10011110111100101110110100111101 $
b10011110111100101110110100111101 *
b10011100100011110110110100111010 !
b10011100100011110110110100111010 +
b111011100000100101101001110111 #
b111011100000100101101001110111 )
b11110 -
b100100111100001011000001001010 %
#155
b10110110111001011000000101101101 $
b10110110111001011000000101101101 *
b10001000000111110111111100010001 !
b10001000000111110111111100010001 +
b111111000001010000000001111110 #
b111111000001010000000001111110 )
b11111 -
b10011100100011110110110100111010 %
#160
b1101001111010111111011011010011 $
b1101001111010111111011011010011 *
b100101111001101001100001001100 !
b100101111001101001100001001100 +
b10001111110100101000111100011111 #
b10001111110100101000111100011111 )
b100000 -
b10001000000111110111111100010001 %
#165
b10101101110110100101100101011011 $
b10101101110110100101100101011011 *
b10001110001110100010111100011101 !
b10001110001110100010111100011101 +
b111100000101001000100001111000 #
b111100000101001000100001111000 )
b100001 -
b100101111001101001100001001100 %
#170
b10010101000011001010111100101010 $
b10010101000011001010111100101010 *
b10001010111001011111111100010101 !
b10001010111001011111111100010101 +
b11111111100101010111000111111 #
b11111111100101010111000111111 )
b100010 -
b10001110001110100010111100011101 %
#175
0&
b1000111000110100000110010001110 $
b1000111000110100000110010001110 *
b10001010010110010100010100010100 !
b10001010010110010100010100010100 +
b1000011001111110011100010000110 #
b1000011001111110011100010000110 )
b100011 -
b10001010111001011111111100010101 %
#180
1&
b10011011111011011110000100110 $
b10011011111011011110000100110 *
b11101001101101111101110111010100 !
b11101001101101111101110111010100 +
b11111101001101011001100111111010 #
b11111101001101011001100111111010 )
b100100 -
b10001010010110010100010100010100 %
#185
0&
b10111100110011010100000101111 $
b10111100110011010100000101111 *
b1101001001001010101110011010010 !
b1101001001001010101110011010010 +
b1010001100010111011010010100011 #
b1010001100010111011010010100011 )
b100101 -
b11101001101101111101110111010100 %
#190
1&
b10100010001010010000110101000100 $
b10100010001010010000110101000100 *
b10001101101011110100100100011011 !
b10001101101011110100100100011011 +
b101111110110000101011001011111 #
b101111110110000101011001011111 )
b100110 -
b1101001001001010101110011010010 %
#195
b1110011000010010001101011100110 $
b1110011000010010001101011100110 *
b11110010100100100001101111100101 !
b11110010100100100001101111100101 +
b1100101100110110011011011001011 #
b1100101100110110011011011001011 )
b100111 -
b10001101101011110100100100011011 %
#200
0&
b1110110100000101110001011101101 $
b1110110100000101110001011101101 *
b1011010100101010010000010110 !
b1011010100101010010000010110 +
b10010100110011111100000100101001 #
b10010100110011111100000100101001 )
b101000 -
b11110010100100100001101111100101 %
#205
b1011010100010101110001010110101 $
b1011010100010101110001010110101 *
b10001101001010101001100100011010 !
b10001101001010101001100100011010 +
b110010100111111011011001100101 #
b110010100111111011011001100101 )
b101001 -
b1011010100101010010000010110 %
#210
b10100010001100011111111101000100 $
b10100010001100011111111101000100 *
b1011111001000110001100010111101 !
b1011111001000110001100010111101 +
b10111100111100010001100101111001 #
b10111100111100010001100101111001 )
b101010 -
b10001101001010101001100100011010 %
#215
1&
b11010101111101101010110110101011 $
b11010101111101101010110110101011 *
b10111111000100100101110101111111 !
b10111111000100100101110101111111 +
b10010101000010010000101100101010 #
b10010101000010010000101100101010 )
b101011 -
b1011111001000110001100010111101 %
#220
0&
b1001101010111101011110010011010 $
b1001101010111101011110010011010 *
b111011101111000110101001110110 !
b111011101111000110101001110110 +
b11101110010111011010110111011100 #
b11101110010111011010110111011100 )
b101100 -
b10111111000100100101110101111111 %
#225
1&
b10101011000011101110110101010110 $
b10101011000011101110110101010110 *
b10110110111000100001010101101101 !
b10110110111000100001010101101101 +
b1100001111100010000001011000011 #
b1100001111100010000001011000011 )
b101101 -
b111011101111000110101001110110 %
#230
b101001100010011010000001010 $
b101001100010011010000001010 *
b101110101010000100001001011101 !
b101110101010000100001001011101 +
b110011110110010111011001100111 #
b110011110110010111011001100111 )
b101110 -
b10110110111000100001010101101101 %
#235
0&
b10111100110100011000011101111001 $
b10111100110100011000011101111001 *
b11011000111000000001000110110001 !
b11011000111000000001000110110001 +
b11100000011101000101000111000 #
b11100000011101000101000111000 )
b101111 -
b101110101010000100001001011101 %
#240
b11001001110001100101110110010011 $
b11001001110001100101110110010011 *
b10010100001110110001110100100111 !
b10010100001110110001110100100111 +
b11001010011101001011111110010100 #
b11001010011101001011111110010100 )
b110000 -
b11011000111000000001000110110001 %
#245
b11101101110010110110100111011011 $
b11101101110010110110100111011011 *
b11010100000110011010000110100 !
b11010100000110011010000110100 +
b101100101101111100101001011001 #
b101100101101111100101001011001 )
b110001 -
b10010100001110110001110100100111 %
#250
b110110101001000010011001101101 $
b110110101001000010011001101101 *
b100011010101001101111001000110 !
b100011010101001101111001000110 +
b11101100101100001011011111011001 #
b11101100101100001011011111011001 )
b110010 -
b11010100000110011010000110100 %
#255
1&
b11011011000101110010110110110110 $
b11011011000101110010110110110110 *
b1010001001000001110000010100 !
b1010001001000001110000010100 +
b11100101001110110100100111001010 #
b11100101001110110100100111001010 )
b110011 -
b100011010101001101111001000110 %
#260
b10000010011101001001101100000100 $
b10000010011101001001101100000100 *
b10100000100100100111111101000010 !
b10100000100100100111111101000010 +
b100011000001110001101001000110 #
b100011000001110001101001000110 )
b110100 -
b1010001001000001110000010100 %
#265
b1011010011011101011101010110100 $
b1011010011011101011101010110100 *
b1011010001010010100110010110101 !
b1011010001010010100110010110101 +
b10110100100110000000011101101001 #
b10110100100110000000011101101001 )
b110101 -
b10100000100100100111111101000010 %
#270
0&
b10110100100000000010000101101 $
b10110100100000000010000101101 *
b10101011000011001101110101010101 !
b10101011000011001101110101010101 +
b10010100011111001101100100101000 #
b10010100011111001101100100101000 )
b110110 -
b1011010001010010100110010110101 %
#275
1&
b100011101111110010000001000 $
b100011101111110010000001000 *
b10010111001001011100000100110 !
b10010111001001011100000100110 +
b10111010111001001110000101110 #
b10111010111001001110000101110 )
b110111 -
b10101011000011001101110101010101 %
#280
0&
b10010100100111100000011100101001 $
b10010100100111100000011100101001 *
b10011010001011010111000100110 !
b10011010001011010111000100110 +
b1111110101001111010011011111101 #
b1111110101001111010011011111101 )
b111000 -
b10010111001001011100000100110 %
#285
b1101101001101000000100011011010 $
b1101101001101000000100011011010 *
b110000011010010111000001100000 !
b110000011010010111000001100000 +
b11000011001101010110011110000110 #
b11000011001101010110011110000110 )
b111001 -
b10011010001011010111000100110 %
#290
b111000010101011100010001110000 $
b111000010101011100010001110000 *
b11101011101001000110101111010110 !
b11101011101001000110101111010110 +
b10110011010011101010011101100110 #
b10110011010011101010011101100110 )
b111010 -
b110000011010010111000001100000 %
#295
1&
b10101111001110101011001101011110 $
b10101111001110101011001101011110 *
b101110001101101110011001011100 !
b101110001101101110011001011100 +
b11011101011100011001100110111010 #
b11011101011100011001100110111010 )
b111011 -
b11101011101001000110101111010110 %
#300
0&
b1101001001001111011000011010 $
b1101001001001111011000011010 *
b11110111101100101111101111101111 !
b11110111101100101111101111101111 +
b11101010100011100000010111010101 #
b11101010100011100000010111010101 )
b111100 -
b101110001101101110011001011100 %
#305
1&
b11001011001001110011011110010110 $
b11001011001001110011011110010110 *
b11010000011000000010100110100001 !
b11010000011000000010100110100001 +
b10011011100001110110000100110111 #
b10011011100001110110000100110111 )
b111101 -
b11110111101100101111101111101111 %
#310
b1011011010001100001101010110110 $
b1011011010001100001101010110110 *
b110111110111111000010001110000 !
b110111110111111000010001110000 +
b10010011001001011001111100100110 #
b10010011001001011001111100100110 )
b111110 -
b11010000011000000010100110100001 %
#315
b11000011011000010101011110000110 $
b11000011011000010101011110000110 *
b101010111111011011100001010110 !
b101010111111011011100001010110 +
b11101110010111110000111111011100 #
b11101110010111110000111111011100 )
b111111 -
b110111110111111000010001110000 %
#320
0&
b1101101100011011000000011011011 $
b1101101100011011000000011011011 *
b101100111010000001110001011001 !
b101100111010000001110001011001 +
b10111111010110101001101101111110 #
b10111111010110101001101101111110 )
b1000000 -
b101010111111011011100001010110 %
#325
b1111101001010001110010011111010 $
b1111101001010001110010011111010 *
b111010000101100001000001110011 !
b111010000101100001000001110011 +
b10111100111011010010101101111001 #
b10111100111011010010101101111001 )
b1000001 -
b101100111010000001110001011001 %
#330
1&
b1010000111101010111100010100001 $
b1010000111101010111100010100001 *
b111010100111101001000001110110 !
b111010100111101001000001110110 +
b10001011100101000000100100010111 #
b10001011100101000000100100010111 )
b1000010 -
b111010000101100001000001110011 %
#335
0&
b11111010100011000101100111110101 $
b11111010100011000101100111110101 *
b100010111011111111000001000101 !
b100010111011111111000001000101 +
b101000011000111001011001010000 #
b101000011000111001011001010000 )
b1000011 -
b111010100111101001000001110110 %
#340
b11100000101100010111010111000001 $
b11100000101100010111010111000001 *
b11110101010010111111111111101010 !
b11110101010010111111111111101010 +
b10100100110101000101000101001 #
b10100100110101000101000101001 )
b1000100 -
b100010111011111111000001000101 %
#345
b10100101101100100111101101001011 $
b10100101101100100111101101001011 *
b11110001101101000010111111100011 !
b11110001101101000010111111100011 +
b1001100000000011011010010011000 #
b1001100000000011011010010011000 )
b1000101 -
b11110101010010111111111111101010 %
#350
1&
b1000101010100000001011010001010 $
b1000101010100000001011010001010 *
b110000110100101101000001100010 !
b110000110100101101000001100010 +
b1110110001000101110011011101100 #
b1110110001000101110011011101100 )
b1000110 -
b11110001101101000010111111100011 %
#355
0&
b11010100100111101111110110101001 $
b11010100100111101111110110101001 *
b101000111010100111111001010001 !
b101000111010100111111001010001 +
b1010100010010111000000010101000 #
b1010100010010111000000010101000 )
b1000111 -
b110000110100101101000001100010 %
#360
b1110011001101000110011011100110 $
b1110011001101000110011011100110 *
b11111010010000000001111111110100 !
b11111010010000000001111111110100 +
b10000111000010111011100100001110 #
b10000111000010111011100100001110 )
b1001000 -
b101000111010100111111001010001 %
#365
b10010101010110100001110100101010 $
b10010101010110100001110100101010 *
b101010100010011101001001010100 !
b101010100010011101001001010100 +
b10010101001011111011010100101010 #
b10010101001011111011010100101010 )
b1001001 -
b11111010010000000001111111110100 %
#370
b11100011011011110011000111000 $
b11100011011011110011000111000 *
b11101011111000111110010111010110 !
b11101011111000111110010111010110 +
b11001111011101011111111110011110 #
b11001111011101011111111110011110 )
b1001010 -
b101010100010011101001001010100 %
#375
1&
b11100101001000110100010111001010 $
b11100101001000110100010111001010 *
b11111111010000011001110111111110 !
b11111111010000011001110111111110 +
b11100100011001001110001111001000 #
b11100100011001001110001111001000 )
b1001011 -
b11101011111000111110010111010110 %
#380
b1100011101101111010111011000111 $
b1100011101101111010111011000111 *
b1010001111010010001101010100100 !
b1010001111010010001101010100100 +
b10110101101000001100100101101011 #
b10110101101000001100100101101011 )
b1001100 -
b11111111010000011001110111111110 %
#385
b11100010000101101010101111000100 $
b11100010000101101010101111000100 *
b11111010111011101111000111110110 !
b11111010111011101111000111110110 +
b11011101000001011001110110111010 #
b11011101000001011001110110111010 )
b1001101 -
b1010001111010010001101010100100 %
#390
b1011010001001101001101010110100 $
b1011010001001101001101010110100 *
b1101111000010010011100011011110 !
b1101111000010010011100011011110 +
b11001001001011111101001110010010 #
b11001001001011111101001110010010 )
b1001110 -
b11111010111011101111000111110110 %
#395
0&
b11111101011011011111010111111010 $
b11111101011011011111010111111010 *
b1000000101000011000011010000000 !
b1000000101000011000011010000000 +
b1000011001100111001000010000110 #
b1000011001100111001000010000110 )
b1001111 -
b1101111000010010011100011011110 %
#400
1&
b1011110110011100101111010111101 $
b1011110110011100101111010111101 *
b111010011101101100001001110101 !
b111010011101101100001001110101 +
b10011001010001010010000100110010 #
b10011001010001010010000100110010 )
b1010000 -
b1000000101000011000011010000000 %
#405
b11100101010000111100111111001010 $
b11100101010000111100111111001010 *
b10001101000001011101010100011010 !
b10001101000001011101010100011010 +
b1110010010010011010010011100100 #
b1110010010010011010010011100100 )
b1010001 -
b111010011101101100001001110101 %
#410
0&
b11000111011001011010100110001110 $
b11000111011001011010100110001110 *
b10111111110110101001000101111 !
b10111111110110101001000101111 +
b1010000100101011010100010100001 #
b1010000100101011010100010100001 )
b1010010 -
b10001101000001011101010100011010 %
#415
1&
b1110111100000101001000011101111 $
b1110111100000101001000011101111 *
b10001110011000101000110100011100 !
b10001110011000101000110100011100 +
b101111001010001111000001011 #
b101111001010001111000001011 )
b1010011 -
b10111111110110101001000101111 %
#420
0&
b111010101100010100100001110101 $
b111010101100010100100001110101 *
b11010110000100100010110110101011 !
b11010110000100100010110110101011 +
b10011011011000001110010100110110 #
b10011011011000001110010100110110 )
b1010100 -
b10001110011000101000110100011100 %
#425
b11000100011001011110011110001000 $
b11000100011001011110011110001000 *
b1111010001100111010011011110011 !
b1111010001100111010011011110011 +
b10110101110011011011111101101011 #
b10110101110011011011111101101011 )
b1010101 -
b11010110000100100010110110101011 %
#430
1&
b11001001001111100100010110010010 $
b11001001001111100100010110010010 *
b100101101010011110000001001 !
b100101101010011110000001001 +
b11001101111100111000000110011011 #
b11001101111100111000000110011011 )
b1010110 -
b1111010001100111010011011110011 %
#435
0&
b10100101101101110101111101001011 $
b10100101101101110101111101001011 *
b10111100001111000011111101111000 !
b10111100001111000011111101111000 +
b10110100001001110000000101101 #
b10110100001001110000000101101 )
b1010111 -
b100101101010011110000001001 %
#440
1&
b10000110101100110000010100001101 $
b10000110101100110000010100001101 *
b10001000011010011111000100010001 !
b10001000011010011111000100010001 +
b1111000111001111011000011110 #
b1111000111001111011000011110 )
b1011000 -
b10111100001111000011111101111000 %
#445
0&
b11101000101011100001101111010001 $
b11101000101011100001101111010001 *
b1110100101100011011100011101001 !
b1110100101100011011100011101001 +
b10001100000000111001110100011000 #
b10001100000000111001110100011000 )
b1011001 -
b10001000011010011111000100010001 %
#450
1&
b11101101111110110010000111011 $
b11101101111110110010000111011 *
b11000000001100000000000110 !
b11000000001100000000000110 +
b100000110000000010010001000001 #
b100000110000000010010001000001 )
b1011010 -
b1110100101100011011100011101001 %
#455
0&
b101011000110010110001001010110 $
b101011000110010110001001010110 *
b11010101000010010100101110101001 !
b11010101000010010100101110101001 +
b10101001111011111110100101010011 #
b10101001111011111110100101010011 )
b1011011 -
b11000000001100000000000110 %
#460
1&
b10011100111110001000000100 $
b10011100111110001000000100 *
b1101110111100110001100011011110 !
b1101110111100110001100011011110 +
b1110001011001101111101011100010 #
b1110001011001101111101011100010 )
b1011100 -
b11010101000010010100101110101001 %
#465
0&
b10001001001111100100110100010010 $
b10001001001111100100110100010010 *
b11110101100011110000000111101010 !
b11110101100011110000000111101010 +
b1101100010100001011010011011000 #
b1101100010100001011010011011000 )
b1011101 -
b1101110111100110001100011011110 %
#470
b1110010100001111011011011100101 $
b1110010100001111011011011100101 *
b10001111000010001100100100011110 !
b10001111000010001100100100011110 +
b11100100000010001001000111001 #
b11100100000010001001000111001 )
b1011110 -
b11110101100011110000000111101010 %
#475
1&
b11000000100100000101110110000001 $
b11000000100100000101110110000001 *
b11010100111110001011000110101010 !
b11010100111110001011000110101010 +
b10010101100010010000111100101011 #
b10010101100010010000111100101011 )
b1011111 -
b10001111000010001100100100011110 %
#480
0&
b11010000110101011111100110100001 $
b11010000110101011111100110100001 *
b1100100100010110100111011001000 !
b1100100100010110100111011001000 +
b10010011101101010101010100100111 #
b10010011101101010101010100100111 )
b1100000 -
b11010100111110001011000110101010 %
#485
b10101100001011010010001101011000 $
b10101100001011010010001101011000 *
b10101110010011110101110101011100 !
b10101110010011110101110101011100 +
b10001000100011101000000100 #
b10001000100011101000000100 )
b1100001 -
b1100100100010110100111011001000 %
#490
b1001000110011011010000010010 $
b1001000110011011010000010010 *
b10010011100010000100011100100110 !
b10010011100010000100011100100110 +
b10001010011011101001001100010100 #
b10001010011011101001001100010100 )
b1100010 -
b10101110010011110101110101011100 %
#495
b10101010110000101101010101010101 $
b10101010110000101101010101010101 *
b11011011111011100000000110 !
b11011011111011100000000110 +
b1011000101011001110001010110001 #
b1011000101011001110001010110001 )
b1100011 -
b10010011100010000100011100100110 %
#500
1&
b11111010101100010001101111110101 $
b11111010101100010001101111110101 *
b10011010110110100000111100110110 !
b10011010110110100000111100110110 +
b10010101100010110010101100101011 #
b10010101100010110010101100101011 )
b1100100 -
b11011011111011100000000110 %
#505
0&
b11000010010010011111111110000100 $
b11000010010010011111111110000100 *
b11010110000010110010000110101011 !
b11010110000010110010000110101011 +
b10011110000010010001000100111 #
b10011110000010010001000100111 )
b1100101 -
b10011010110110100000111100110110 %
#510
b1011100111011111001000010111001 $
b1011100111011111001000010111001 *
b11010000110001110011011110100000 !
b11010000110001110011011110100000 +
b1110011110101111010011011100111 #
b1110011110101111010011011100111 )
b1100110 -
b11010110000010110010000110101011 %
#515
1&
b11100100101110100000111111001001 $
b11100100101110100000111111001001 *
b1001001010111010110000010010 !
b1001001010111010110000010010 +
b11101101111001011011101111011011 #
b11101101111001011011101111011011 )
b1100111 -
b11010000110001110011011110100000 %
#520
b10010101010001101101110100101010 $
b10010101010001101101110100101010 *
b10111011011101011000000101110111 !
b10111011011101011000000101110111 +
b1010000101111000101111010100001 #
b1010000101111000101111010100001 )
b1101000 -
b1001001010111010110000010010 %
#525
0&
b11000001101000010000010110000011 $
b11000001101000010000010110000011 *
b11100100100001110010010111001000 !
b11100100100001110010010111001000 +
b100010111001100010000001000101 #
b100010111001100010000001000101 )
b1101001 -
b10111011011101011000000101110111 %
#530
b1111111010011110011110011111110 $
b1111111010011110011110011111110 *
b10111000100101010101000101110000 !
b10111000100101010101000101110000 +
b111001010001100001010001110010 #
b111001010001100001010001110010 )
b1101010 -
b11100100100001110010010111001000 %
#535
1&
b11000011010001100000110110000110 $
b11000011010001100000110110000110 *
b1110100100110011001110011101001 !
b1110100100110011001110011101001 +
b110111110111111010101001101111 #
b110111110111111010101001101111 )
b1101011 -
b10111000100101010101000101110000 %
#540
0&
b10100000011101101001000101000000 $
b10100000011101101001000101000000 *
b111100111010000010100001111000 !
b111100111010000010100001111000 +
b10011100011100011001011100111000 #
b10011100011100011001011100111000 )
b1101100 -
b1110100100110011001110011101001 %
#545
1&
b1100010101111110001101011000101 $
b1100010101111110001101011000101 *
b10011000010011101000111100110001 !
b10011000010011101000111100110001 +
b11111011000011011010100111110110 #
b11111011000011011010100111110110 )
b1101101 -
b111100111010000010100001111000 %
#550
0&
b10011100110111100111000100111001 $
b10011100110111100111000100111001 *
b1010111010000001101000010101101 !
b1010111010000001101000010101101 +
b10111010011000100101111101110100 #
b10111010011000100101111101110100 )
b1101110 -
b10011000010011101000111100110001 %
#555
1&
b10010101001000011001001100101010 $
b10010101001000011001001100101010 *
b1000111110101111010000010010 !
b1000111110101111010000010010 +
b10011110000111001000011100111100 #
b10011110000111001000011100111100 )
b1101111 -
b1010111010000001101000010101101 %
#560
b1110000101100010100111011100001 $
b1110000101100010100111011100001 *
b11010001110101110011000110100 !
b11010001110101110011000110100 +
b10001010111011000011010100010101 #
b10001010111011000011010100010101 )
b1110000 -
b1000111110101111010000010010 %
#565
0&
b11100100101101011110001111001001 $
b11100100101101011110001111001001 *
b110010000011101001000001100 !
b110010000011101001000001100 +
b100001100010111110111001000011 #
b100001100010111110111001000011 )
b1110001 -
b11010001110101110011000110100 %
#570
b11100000111101101001110111000001 $
b11100000111101101001110111000001 *
b1110011100011100110100011100110 !
b1110011100011100110100011100110 +
b10010010100101111100101100100101 #
b10010010100101111100101100100101 )
b1110010 -
b110010000011101001000001100 %
#575
1&
b10000011110101100010011100000111 $
b10000011110101100010011100000111 *
b10101001100100011011101101010011 !
b10101001100100011011101101010011 +
b101101011001111110001001011010 #
b101101011001111110001001011010 )
b1110011 -
b1110011100011100110100011100110 %
#580
0&
b111000101011011110011001110001 $
b111000101011011110011001110001 *
b10111110101110000100001101111101 !
b10111110101110000100001101111101 +
b10000110000010100101110100001100 #
b10000110000010100101110100001100 )
b1110100 -
b10101001100100011011101101010011 %
#585
b1111011110111111100001011110111 $
b1111011110111111100001011110111 *
b1010111010000001010100010101101 !
b1010111010000001010100010101101 +
b11011011011000001110010110110110 #
b11011011011000001110010110110110 )
b1110101 -
b10111110101110000100001101111101 %
#590
b10101010101110001111011101010101 $
b10101010101110001111011101010101 *
b11011001001100010100111110110001 !
b11011001001100010100111110110001 +
b101110011110000101100001011100 #
b101110011110000101100001011100 )
b1110110 -
b1010111010000001010100010101101 %
#595
b10111001011000000000100101110010 $
b10111001011000000000100101110010 *
b1001011010110001110000010010 !
b1001011010110001110000010010 +
b1010000000010110001001010100000 #
b1010000000010110001001010100000 )
b1110111 -
b11011001001100010100111110110001 %
#600
1&
b110110111001111000000001101 $
b110110111001111000000001101 *
b11100111101011100000010111010000 !
b11100111101011100000010111010000 +
b11101110100010101111010111011101 #
b11101110100010101111010111011101 )
b1111000 -
b1001011010110001110000010010 %
